{"annotation": {"filename": "000347.jpg", "folder": "users/TJohnsenSJSU//wildfire", "source": {"submittedBy": "Timothy Johnsen"}, "imagesize": {"nrows": "540", "ncols": "960"}, "object": [{"name": "fire", "deleted": "0", "verified": "0", "occluded": "no", "attributes": null, "parts": {"hasparts": null, "ispartof": null}, "date": "28-01-21 15:52:17:146", "id": "0", "polygon": {"username": "tim", "pt": [{"x": "572", "y": "345", "time": "28-01-21 15:52:14:623"}, {"x": "568", "y": "332", "time": "28-01-21 15:52:14:854"}, {"x": "572", "y": "319", "time": "28-01-21 15:52:15:045"}, {"x": "586", "y": "305", "time": "28-01-21 15:52:15:222"}, {"x": "597", "y": "309", "time": "28-01-21 15:52:15:397"}, {"x": "593", "y": "326", "time": "28-01-21 15:52:15:605"}, {"x": "588", "y": "342", "time": "28-01-21 15:52:15:805"}, {"x": "580", "y": "351", "time": "28-01-21 15:52:16:006"}], "closed_date": "28-01-21 15:52:16:198"}}, {"name": "smoke", "deleted": "0", "verified": "0", "occluded": "no", "attributes": null, "parts": {"hasparts": null, "ispartof": null}, "date": "28-01-21 15:52:32:984", "id": "1", "polygon": {"username": "tim", "pt": [{"x": "596", "y": "302", "time": "28-01-21 15:52:18:752"}, {"x": "602", "y": "262", "time": "28-01-21 15:52:18:998"}, {"x": "606", "y": "234", "time": "28-01-21 15:52:19:199"}, {"x": "610", "y": "204", "time": "28-01-21 15:52:19:382"}, {"x": "597", "y": "172", "time": "28-01-21 15:52:19:566"}, {"x": "601", "y": "147", "time": "28-01-21 15:52:19:758"}, {"x": "617", "y": "129", "time": "28-01-21 15:52:20:014"}, {"x": "637", "y": "128", "time": "28-01-21 15:52:20:198"}, {"x": "659", "y": "133", "time": "28-01-21 15:52:20:399"}, {"x": "696", "y": "113", "time": "28-01-21 15:52:20:574"}, {"x": "704", "y": "90", "time": "28-01-21 15:52:20:759"}, {"x": "699", "y": "56", "time": "28-01-21 15:52:20:967"}, {"x": "696", "y": "22", "time": "28-01-21 15:52:21:166"}, {"x": "667", "y": "12", "time": "28-01-21 15:52:21:375"}, {"x": "640", "y": "9", "time": "28-01-21 15:52:21:607"}, {"x": "596", "y": "6", "time": "28-01-21 15:52:21:943"}, {"x": "581", "y": "8", "time": "28-01-21 15:52:22:903"}, {"x": "566", "y": "21", "time": "28-01-21 15:52:23:087"}, {"x": "501", "y": "13", "time": "28-01-21 15:52:23:255"}, {"x": "453", "y": "7", "time": "28-01-21 15:52:23:479"}, {"x": "403", "y": "5", "time": "28-01-21 15:52:23:679"}, {"x": "367", "y": "7", "time": "28-01-21 15:52:23:863"}, {"x": "347", "y": "50", "time": "28-01-21 15:52:24:046"}, {"x": "330", "y": "97", "time": "28-01-21 15:52:24:248"}, {"x": "349", "y": "157", "time": "28-01-21 15:52:24:439"}, {"x": "351", "y": "194", "time": "28-01-21 15:52:24:647"}, {"x": "363", "y": "225", "time": "28-01-21 15:52:24:840"}, {"x": "379", "y": "238", "time": "28-01-21 15:52:25:015"}, {"x": "355", "y": "262", "time": "28-01-21 15:52:25:207"}, {"x": "334", "y": "260", "time": "28-01-21 15:52:25:399"}, {"x": "310", "y": "264", "time": "28-01-21 15:52:25:583"}, {"x": "289", "y": "304", "time": "28-01-21 15:52:25:775"}, {"x": "283", "y": "332", "time": "28-01-21 15:52:25:967"}, {"x": "282", "y": "349", "time": "28-01-21 15:52:26:159"}, {"x": "285", "y": "383", "time": "28-01-21 15:52:26:368"}, {"x": "307", "y": "395", "time": "28-01-21 15:52:26:591"}, {"x": "349", "y": "394", "time": "28-01-21 15:52:26:815"}, {"x": "381", "y": "379", "time": "28-01-21 15:52:27:024"}, {"x": "406", "y": "364", "time": "28-01-21 15:52:27:208"}, {"x": "411", "y": "361", "time": "28-01-21 15:52:27:431"}, {"x": "422", "y": "353", "time": "28-01-21 15:52:27:640"}, {"x": "430", "y": "345", "time": "28-01-21 15:52:27:992"}, {"x": "451", "y": "340", "time": "28-01-21 15:52:28:215"}, {"x": "458", "y": "332", "time": "28-01-21 15:52:28:488"}, {"x": "467", "y": "303", "time": "28-01-21 15:52:28:719"}, {"x": "480", "y": "286", "time": "28-01-21 15:52:28:936"}, {"x": "492", "y": "267", "time": "28-01-21 15:52:29:144"}, {"x": "507", "y": "268", "time": "28-01-21 15:52:29:336"}, {"x": "523", "y": "265", "time": "28-01-21 15:52:29:528"}, {"x": "536", "y": "248", "time": "28-01-21 15:52:29:728"}, {"x": "542", "y": "240", "time": "28-01-21 15:52:29:920"}, {"x": "542", "y": "264", "time": "28-01-21 15:52:30:128"}, {"x": "542", "y": "283", "time": "28-01-21 15:52:30:320"}, {"x": "545", "y": "299", "time": "28-01-21 15:52:30:536"}, {"x": "556", "y": "295", "time": "28-01-21 15:52:30:784"}, {"x": "566", "y": "295", "time": "28-01-21 15:52:30:968"}, {"x": "567", "y": "309", "time": "28-01-21 15:52:31:176"}, {"x": "576", "y": "310", "time": "28-01-21 15:52:31:392"}, {"x": "588", "y": "299", "time": "28-01-21 15:52:31:584"}], "closed_date": "28-01-21 15:52:31:760"}}, {"name": "fire", "deleted": "0", "verified": "0", "occluded": "no", "attributes": null, "parts": {"hasparts": null, "ispartof": null}, "date": "28-01-21 15:52:37:086", "id": "2", "polygon": {"username": "tim", "pt": [{"x": "421", "y": "364", "time": "28-01-21 15:52:34:386"}, {"x": "440", "y": "351", "time": "28-01-21 15:52:34:673"}, {"x": "456", "y": "354", "time": "28-01-21 15:52:34:985"}, {"x": "467", "y": "360", "time": "28-01-21 15:52:35:321"}, {"x": "437", "y": "367", "time": "28-01-21 15:52:35:729"}], "closed_date": "28-01-21 15:52:36:121"}}]}}