{"annotation": {"filename": "000552.jpg", "folder": "users/TJohnsenSJSU//wildfire", "source": {"submittedBy": "Timothy Johnsen"}, "imagesize": {"nrows": "360", "ncols": "640"}, "object": {"name": "smoke", "deleted": "0", "verified": "0", "occluded": "no", "attributes": null, "parts": {"hasparts": null, "ispartof": null}, "date": "28-01-21 16:33:57:642", "id": "0", "polygon": {"username": "tim", "pt": [{"x": "638", "y": "108", "time": "28-01-21 16:33:44:112"}, {"x": "365", "y": "78", "time": "28-01-21 16:33:44:847"}, {"x": "338", "y": "85", "time": "28-01-21 16:33:45:367"}, {"x": "315", "y": "68", "time": "28-01-21 16:33:45:831"}, {"x": "306", "y": "89", "time": "28-01-21 16:33:46:287"}, {"x": "284", "y": "83", "time": "28-01-21 16:33:46:879"}, {"x": "231", "y": "118", "time": "28-01-21 16:33:47:575"}, {"x": "217", "y": "86", "time": "28-01-21 16:33:48:295"}, {"x": "185", "y": "116", "time": "28-01-21 16:33:49:184"}, {"x": "154", "y": "117", "time": "28-01-21 16:33:49:935"}, {"x": "169", "y": "214", "time": "28-01-21 16:33:50:663"}, {"x": "264", "y": "232", "time": "28-01-21 16:33:51:352"}, {"x": "282", "y": "284", "time": "28-01-21 16:33:52:112"}, {"x": "391", "y": "273", "time": "28-01-21 16:33:52:823"}, {"x": "436", "y": "306", "time": "28-01-21 16:33:53:424"}, {"x": "635", "y": "324", "time": "28-01-21 16:33:54:440"}], "closed_date": "28-01-21 16:33:55:985"}}}}