{"annotation": {"filename": "000890.jpg", "folder": "users/TJohnsenSJSU//wildfire", "source": {"submittedBy": "Timothy Johnsen"}, "imagesize": {"nrows": "360", "ncols": "640"}, "object": [{"name": "smoke", "deleted": "0", "verified": "0", "occluded": "no", "attributes": null, "parts": {"hasparts": null, "ispartof": null}, "date": "28-01-21 17:01:49:283", "id": "0", "polygon": {"username": "tim", "pt": [{"x": "357", "y": "257", "time": "28-01-21 17:01:41:324"}, {"x": "351", "y": "249", "time": "28-01-21 17:01:41:531"}, {"x": "344", "y": "239", "time": "28-01-21 17:01:41:707"}, {"x": "333", "y": "226", "time": "28-01-21 17:01:41:932"}, {"x": "338", "y": "208", "time": "28-01-21 17:01:42:139"}, {"x": "345", "y": "195", "time": "28-01-21 17:01:42:348"}, {"x": "355", "y": "189", "time": "28-01-21 17:01:42:556"}, {"x": "356", "y": "178", "time": "28-01-21 17:01:42:755"}, {"x": "335", "y": "181", "time": "28-01-21 17:01:42:940"}, {"x": "326", "y": "185", "time": "28-01-21 17:01:43:140"}, {"x": "319", "y": "170", "time": "28-01-21 17:01:43:299"}, {"x": "326", "y": "150", "time": "28-01-21 17:01:43:523"}, {"x": "328", "y": "131", "time": "28-01-21 17:01:43:716"}, {"x": "357", "y": "119", "time": "28-01-21 17:01:43:964"}, {"x": "367", "y": "113", "time": "28-01-21 17:01:44:364"}, {"x": "378", "y": "97", "time": "28-01-21 17:01:44:548"}, {"x": "397", "y": "98", "time": "28-01-21 17:01:44:756"}, {"x": "415", "y": "114", "time": "28-01-21 17:01:44:940"}, {"x": "433", "y": "116", "time": "28-01-21 17:01:45:140"}, {"x": "462", "y": "124", "time": "28-01-21 17:01:45:356"}, {"x": "484", "y": "123", "time": "28-01-21 17:01:45:540"}, {"x": "495", "y": "139", "time": "28-01-21 17:01:45:740"}, {"x": "460", "y": "160", "time": "28-01-21 17:01:45:940"}, {"x": "435", "y": "174", "time": "28-01-21 17:01:46:124"}, {"x": "431", "y": "191", "time": "28-01-21 17:01:46:324"}, {"x": "421", "y": "202", "time": "28-01-21 17:01:46:516"}, {"x": "401", "y": "201", "time": "28-01-21 17:01:46:724"}, {"x": "384", "y": "205", "time": "28-01-21 17:01:46:924"}, {"x": "377", "y": "221", "time": "28-01-21 17:01:47:108"}, {"x": "377", "y": "230", "time": "28-01-21 17:01:47:308"}, {"x": "373", "y": "246", "time": "28-01-21 17:01:47:508"}, {"x": "365", "y": "253", "time": "28-01-21 17:01:47:708"}, {"x": "361", "y": "255", "time": "28-01-21 17:01:47:932"}], "closed_date": "28-01-21 17:01:48:309"}}, {"name": "smoke", "deleted": "0", "verified": "0", "occluded": "no", "attributes": null, "parts": {"hasparts": null, "ispartof": null}, "date": "28-01-21 17:01:52:470", "id": "1", "polygon": {"username": "tim", "pt": [{"x": "403", "y": "280", "time": "28-01-21 17:01:49:806"}, {"x": "396", "y": "278", "time": "28-01-21 17:01:49:989"}, {"x": "395", "y": "266", "time": "28-01-21 17:01:50:197"}, {"x": "411", "y": "260", "time": "28-01-21 17:01:50:405"}, {"x": "421", "y": "255", "time": "28-01-21 17:01:50:613"}, {"x": "432", "y": "262", "time": "28-01-21 17:01:50:813"}, {"x": "428", "y": "271", "time": "28-01-21 17:01:51:037"}, {"x": "423", "y": "279", "time": "28-01-21 17:01:51:253"}, {"x": "412", "y": "281", "time": "28-01-21 17:01:51:453"}], "closed_date": "28-01-21 17:01:51:709"}}, {"name": "smoke", "deleted": "0", "verified": "0", "occluded": "no", "attributes": null, "parts": {"hasparts": null, "ispartof": null}, "date": "28-01-21 17:01:55:771", "id": "2", "polygon": {"username": "tim", "pt": [{"x": "491", "y": "315", "time": "28-01-21 17:01:53:119"}, {"x": "485", "y": "304", "time": "28-01-21 17:01:53:309"}, {"x": "504", "y": "284", "time": "28-01-21 17:01:53:525"}, {"x": "542", "y": "261", "time": "28-01-21 17:01:53:734"}, {"x": "575", "y": "242", "time": "28-01-21 17:01:53:950"}, {"x": "598", "y": "240", "time": "28-01-21 17:01:54:165"}, {"x": "568", "y": "272", "time": "28-01-21 17:01:54:454"}, {"x": "551", "y": "292", "time": "28-01-21 17:01:54:646"}, {"x": "533", "y": "306", "time": "28-01-21 17:01:54:853"}], "closed_date": "28-01-21 17:01:55:046"}}, {"name": "smoke", "deleted": "0", "verified": "0", "occluded": "no", "attributes": null, "parts": {"hasparts": null, "ispartof": null}, "date": "28-01-21 17:01:59:492", "id": "3", "polygon": {"username": "tim", "pt": [{"x": "232", "y": "284", "time": "28-01-21 17:01:56:631"}, {"x": "220", "y": "275", "time": "28-01-21 17:01:56:862"}, {"x": "208", "y": "266", "time": "28-01-21 17:01:57:062"}, {"x": "203", "y": "246", "time": "28-01-21 17:01:57:286"}, {"x": "214", "y": "233", "time": "28-01-21 17:01:57:486"}, {"x": "231", "y": "230", "time": "28-01-21 17:01:57:679"}, {"x": "242", "y": "247", "time": "28-01-21 17:01:57:887"}, {"x": "228", "y": "261", "time": "28-01-21 17:01:58:086"}, {"x": "233", "y": "274", "time": "28-01-21 17:01:58:326"}, {"x": "231", "y": "279", "time": "28-01-21 17:01:58:598"}], "closed_date": "28-01-21 17:01:58:806"}}, {"name": "smoke", "deleted": "0", "verified": "0", "occluded": "no", "attributes": null, "parts": {"hasparts": null, "ispartof": null}, "date": "28-01-21 17:02:02:295", "id": "4", "polygon": {"username": "tim", "pt": [{"x": "173", "y": "181", "time": "28-01-21 17:01:59:968"}, {"x": "160", "y": "170", "time": "28-01-21 17:02:00:175"}, {"x": "153", "y": "150", "time": "28-01-21 17:02:00:374"}, {"x": "171", "y": "139", "time": "28-01-21 17:02:00:614"}, {"x": "184", "y": "136", "time": "28-01-21 17:02:00:831"}, {"x": "205", "y": "135", "time": "28-01-21 17:02:01:031"}, {"x": "192", "y": "154", "time": "28-01-21 17:02:01:231"}, {"x": "174", "y": "175", "time": "28-01-21 17:02:01:415"}], "closed_date": "28-01-21 17:02:01:615"}}]}}